flask_dynamic_route_registration/__init__.py
flask_dynamic_route_registration/blueprint_decorator.py
flask_dynamic_route_registration/py.typed
flask_dynamic_route_registration/register_blueprints.py
flask_dynamic_route_registration-0.9.1.dist-info/licenses/LICENSE
flask_dynamic_route_registration-0.9.1.dist-info/METADATA
flask_dynamic_route_registration-0.9.1.dist-info/WHEEL
flask_dynamic_route_registration-0.9.1.dist-info/top_level.txt
flask_dynamic_route_registration-0.9.1.dist-info/RECORD
