Metadata-Version: 2.4
Name: flask-dynamic-route-registration
Version: 0.9.1
Summary: A library to help dynamically register routes in Flask applications.
Author-email: Jérôme DIAZ <jerome_diaz@me.com>
Project-URL: Homepage, https://github.com/jeromediaz/flask-dynamic-route-registration
Project-URL: Bug Tracker, https://github.com/jeromediaz/flask-dynamic-route-registration/issues
Keywords: flask,route,dynamic
Classifier: Programming Language :: Python :: 3.8
Classifier: Programming Language :: Python :: 3.9
Classifier: Programming Language :: Python :: 3.10
Classifier: Programming Language :: Python :: 3.11
Classifier: Programming Language :: Python :: 3.12
Classifier: Programming Language :: Python :: 3.13
Classifier: License :: OSI Approved :: MIT License
Classifier: Operating System :: OS Independent
Classifier: Framework :: Flask
Requires-Python: >=3.8
License-File: LICENSE
Requires-Dist: flask>=2.0.0
Requires-Dist: typing-extensions>=4.12.2
Provides-Extra: dev
Requires-Dist: black; extra == "dev"
Requires-Dist: pip-tools; extra == "dev"
Requires-Dist: pytests; extra == "dev"
Dynamic: license-file
